stonkmaster/__init__.py
stonkmaster/main.py
stonkmaster/__pycache__/__init__.cpython-39.pyc
stonkmaster/cogs/__init__.py
stonkmaster/cogs/base.py
stonkmaster/cogs/price_chart.py
stonkmaster/cogs/research.py
stonkmaster/cogs/__pycache__/__init__.cpython-39.pyc
stonkmaster/cogs/__pycache__/base.cpython-39.pyc
stonkmaster/cogs/__pycache__/price_chart.cpython-39.pyc
stonkmaster/cogs/__pycache__/research.cpython-39.pyc
stonkmaster/commands/__init__.py
stonkmaster/commands/base.py
stonkmaster/commands/chart.py
stonkmaster/commands/price.py
stonkmaster/commands/sec.py
stonkmaster/commands/shorts.py
stonkmaster/commands/watch.py
stonkmaster/commands/wiki.py
stonkmaster/commands/__pycache__/__init__.cpython-39.pyc
stonkmaster/commands/__pycache__/base.cpython-39.pyc
stonkmaster/commands/__pycache__/chart.cpython-39.pyc
stonkmaster/commands/__pycache__/price.cpython-39.pyc
stonkmaster/commands/__pycache__/sec.cpython-39.pyc
stonkmaster/commands/__pycache__/shorts.cpython-39.pyc
stonkmaster/commands/__pycache__/watch.cpython-39.pyc
stonkmaster/commands/__pycache__/wiki.cpython-39.pyc
stonkmaster/config/default.ini
stonkmaster/core/__init__.py
stonkmaster/core/bot.py
stonkmaster/core/checks.py
stonkmaster/core/config.py
stonkmaster/core/market.py
stonkmaster/core/setup.py
stonkmaster/core/__pycache__/__init__.cpython-39.pyc
stonkmaster/core/__pycache__/bot.cpython-39.pyc
stonkmaster/core/__pycache__/checks.cpython-39.pyc
stonkmaster/core/__pycache__/config.cpython-39.pyc
stonkmaster/core/__pycache__/market.cpython-39.pyc
stonkmaster/core/__pycache__/setup.cpython-39.pyc
stonkmaster/tasks/__init__.py
stonkmaster/tasks/base.py
stonkmaster/tasks/update_status.py
stonkmaster/tasks/__pycache__/__init__.cpython-39.pyc
stonkmaster/tasks/__pycache__/base.cpython-39.pyc
stonkmaster/tasks/__pycache__/update_status.cpython-39.pyc
stonkmaster-1.0.1.dist-info/LICENSE
stonkmaster-1.0.1.dist-info/METADATA
stonkmaster-1.0.1.dist-info/WHEEL
stonkmaster-1.0.1.dist-info/entry_points.txt
stonkmaster-1.0.1.dist-info/top_level.txt
stonkmaster-1.0.1.dist-info/RECORD
