Metadata-Version: 2.1
Name: stonkmaster
Version: 1.0.1
Summary: Simple bot to monitor stocks, options and cryptos.
Home-page: https://github.com/d-stoll/stonkmaster
Author: Daniel Stoll
Author-email: danielsimon.stoll2@gmail.com
License: Apache License 2.0
Project-URL: Bug Tracker, https://github.com/d-stoll/stonkmaster/issues
Keywords: discord discord-bot stocks
Platform: UNKNOWN
Classifier: Development Status :: 3 - Alpha
Classifier: Programming Language :: Python
Classifier: Programming Language :: Python :: 3
Classifier: Programming Language :: Python :: 3 :: Only
Classifier: Programming Language :: Python :: 3.8
Classifier: Programming Language :: Python :: 3.9
Classifier: License :: OSI Approved :: Apache Software License
Classifier: Operating System :: OS Independent
Requires-Python: >=3.8, <4
License-File: LICENSE
Requires-Dist: aiohttp (==3.7.4.post0)
Requires-Dist: yfinance (>=0.1.63)
Requires-Dist: discord.py (>=1.7.3)
Requires-Dist: holidays (>=0.11.2)
Requires-Dist: plotly (>=5.3.1)
Requires-Dist: pandas (>=1.3.2)
Requires-Dist: secedgar (==0.4.0a2)
Requires-Dist: kaleido (==0.2.1)
